donn/__init__.py
donn/base_model.py
donn/data.py
donn/donn_tools.py
donn/layers.py
donn/main.py
donn-1.1.8.dist-info/METADATA
donn-1.1.8.dist-info/RECORD
donn-1.1.8.dist-info/WHEEL
donn-1.1.8.dist-info/top_level.txt
