Metadata-Version: 2.1
Name: donn
Version: 1.1.8
Summary: Deep Optimized Neural Networks
Home-page: https://github.com/sharan-amutharasu/donn
Author: Sharan Amutharasu
Author-email: sharan.amutharasu@gmail.com
License: MIT
Download-URL: https://github.com/sharan-amutharasu/donn/tarball/1.1.1
Platform: UNKNOWN
Classifier: Intended Audience :: Developers
Classifier: Intended Audience :: Education
Classifier: Intended Audience :: Science/Research
Classifier: Programming Language :: Python :: 3
Classifier: Topic :: Software Development :: Libraries
Classifier: Topic :: Software Development :: Libraries :: Python Modules
Provides-Extra: tests
Requires-Dist: keras (>=2.2.0)
Requires-Dist: numpy (>=1.9.1)
Requires-Dist: scipy (>=0.14)
Requires-Dist: six (>=1.9.0)
Requires-Dist: pyyaml
Requires-Dist: h5py
Requires-Dist: scikit-learn (>=0.19.0)
Provides-Extra: tests
Requires-Dist: pytest; extra == 'tests'
